README.rst
setup.py
pygments_shader/__init__.py
pygments_shader/lexer.py
pygments_shader.egg-info/PKG-INFO
pygments_shader.egg-info/SOURCES.txt
pygments_shader.egg-info/dependency_links.txt
pygments_shader.egg-info/entry_points.txt
pygments_shader.egg-info/requires.txt
pygments_shader.egg-info/top_level.txt