Metadata-Version: 1.1
Name: pygments-shader
Version: 1.0.1
Summary: Pygments lexer for Unity shader
Home-page: https://github.com/midnightSuyama/pygments-shader
Author: midnightSuyama
Author-email: midnightSuyama@gmail.com
License: MIT
Keywords: pygments shader unity
Platform: UNKNOWN
Classifier: Environment :: Plugins
Classifier: License :: OSI Approved :: MIT License
